uta_tools/__init__.py
uta_tools/main.py
uta_tools/schemas.py
uta_tools/uta_tools.py
uta_tools/version.py
uta_tools/data/__init__.py
uta_tools/data/data_downloads.py
uta_tools/data/transcript_mapping.tsv
uta_tools/data_sources/__init__.py
uta_tools/data_sources/gene_normalizer.py
uta_tools/data_sources/mane_transcript.py
uta_tools/data_sources/mane_transcript_mappings.py
uta_tools/data_sources/residue_mode.py
uta_tools/data_sources/seqrepo_access.py
uta_tools/data_sources/transcript_mappings.py
uta_tools/data_sources/uta_database.py
uta_tools-0.1.3.dist-info/LICENSE
uta_tools-0.1.3.dist-info/METADATA
uta_tools-0.1.3.dist-info/WHEEL
uta_tools-0.1.3.dist-info/top_level.txt
uta_tools-0.1.3.dist-info/RECORD
