Metadata-Version: 2.1
Name: uta-tools
Version: 0.1.3
Summary: Service for querying the biocommons.uta database
Home-page: https://github.com/cancervariants/uta_tools
Author: Wagner Lab, Nationwide Childrens Hospital
License: MIT
Requires-Python: >=3.8
License-File: LICENSE
Requires-Dist: asyncpg
Requires-Dist: aiofiles
Requires-Dist: boto3
Requires-Dist: pyliftover
Requires-Dist: pandas
Requires-Dist: hgvs
Requires-Dist: biocommons.seqrepo
Requires-Dist: pydantic
Requires-Dist: uvicorn
Requires-Dist: fastapi
Requires-Dist: gene-normalizer
Provides-Extra: dev
Requires-Dist: pytest ; extra == 'dev'
Requires-Dist: pytest-cov ; extra == 'dev'
Requires-Dist: psycopg2-binary ; extra == 'dev'
